speaker_recognition/__init__.py
speaker_recognition/__main__.py
speaker_recognition/api.py
speaker_recognition/client.py
speaker_recognition/const.py
speaker_recognition/logging_config.py
speaker_recognition/models.py
speaker_recognition/py.typed
speaker_recognition/recognizer.py
hass_speaker_recognition-1.0.12.dist-info/LICENSE.md
hass_speaker_recognition-1.0.12.dist-info/METADATA
hass_speaker_recognition-1.0.12.dist-info/WHEEL
hass_speaker_recognition-1.0.12.dist-info/top_level.txt
hass_speaker_recognition-1.0.12.dist-info/RECORD
