Metadata-Version: 2.1
Name: hass-speaker-recognition
Version: 1.0.12
Summary: Speaker recognition for Home Assistant using Resemblyzer
Requires-Python: >=3.8
License-File: LICENSE.md
Requires-Dist: httpx >=0.24.0
Requires-Dist: pydantic >=2.0.0
Provides-Extra: server
Requires-Dist: fastapi >=0.68.1 ; extra == 'server'
Requires-Dist: python-dotenv >=0.20.0 ; extra == 'server'
Requires-Dist: setuptools <81,>=59.6.0 ; extra == 'server'
Requires-Dist: typer >=0.10.0 ; extra == 'server'
Requires-Dist: uvicorn >=0.16.0 ; extra == 'server'
Requires-Dist: torch <3.0.0,>=1.9.0 ; (python_version < "3.10") and extra == 'server'
Requires-Dist: resemblyzer >=0.1.3 ; (python_version < "3.10") and extra == 'server'
